{
    "homepage": "https://www.xyplorer.com/index.php",
    "version": "24.00.0500",
    "description": "A file manager for Windows.",
    "license": {
        "identifier": "Proprietary",
        "url": "https://www.xyplorer.com/LicenseXY.txt"
    },
    "url": "https://www.xyplorer.com/download/xyplorer_full_noinstall.zip",
    "hash": "434176686d40c57000ca87ccd53c298ce57622320692136e6aea8d1918c97f33",
    "bin": "XYplorer.exe",
    "shortcuts": [
        [
            "XYplorer.exe",
            "XYplorer"
        ]
    ],
    "persist": "Data",
    "checkver": {
        "url": "https://www.xyplorer.com/download.php",
        "re": "([\\d.]+),\\s*released"
    },
    "autoupdate": {
        "url": "https://www.xyplorer.com/download/xyplorer_full_noinstall.zip"
    }
}
